app.py
predict.py
test.py
train.py
nougat/__init__.py
nougat/_version.py
nougat/metrics.py
nougat/model.py
nougat/postprocessing.py
nougat/transforms.py
nougat/dataset/__init__.py
nougat/dataset/create_index.py
nougat/dataset/gen_seek.py
nougat/dataset/pdffigures.py
nougat/dataset/rasterize.py
nougat/dataset/split_htmls_to_pages.py
nougat/dataset/split_md_to_pages.py
nougat/dataset/splitter.py
nougat/dataset/staircase.py
nougat/dataset/parser/__init__.py
nougat/dataset/parser/document.py
nougat/dataset/parser/html2md.py
nougat/dataset/parser/latexml_parser.py
nougat/dataset/parser/markdown.py
nougat/dataset/utils/__init__.py
nougat/dataset/utils/latex_conversion.py
nougat/dataset/utils/pdf_text_extract.py
nougat/dataset/utils/utils.py
nougat/utils/__init__.py
nougat/utils/checkpoint.py
nougat/utils/dataset.py
nougat/utils/device.py
nougat_ocr-0.1.17.dist-info/LICENSE
nougat_ocr-0.1.17.dist-info/LICENSE-MODEL.md
nougat_ocr-0.1.17.dist-info/METADATA
nougat_ocr-0.1.17.dist-info/NOTICE
nougat_ocr-0.1.17.dist-info/WHEEL
nougat_ocr-0.1.17.dist-info/entry_points.txt
nougat_ocr-0.1.17.dist-info/top_level.txt
nougat_ocr-0.1.17.dist-info/RECORD
