Metadata-Version: 2.1
Name: nougat-ocr
Version: 0.1.17
Summary: Nougat: Neural Optical Understanding for Academic Documents
Home-page: https://github.com/facebookresearch/nougat
Author: Lukas Blecher
Author-email: lblecher@meta.com
License: MIT
Classifier: Intended Audience :: Developers
Classifier: Intended Audience :: Information Technology
Classifier: Intended Audience :: Science/Research
Classifier: License :: OSI Approved :: MIT License
Classifier: Programming Language :: Python
Classifier: Programming Language :: Python :: 3
Classifier: Programming Language :: Python :: 3.7
Classifier: Programming Language :: Python :: 3.8
Classifier: Programming Language :: Python :: 3.9
Classifier: Programming Language :: Python :: 3.10
Classifier: Topic :: Scientific/Engineering :: Artificial Intelligence
Classifier: Topic :: Software Development :: Libraries
Classifier: Topic :: Software Development :: Libraries :: Python Modules
Requires-Python: >=3.7
License-File: LICENSE
License-File: LICENSE-MODEL.md
License-File: NOTICE
Requires-Dist: transformers >=4.25.1
Requires-Dist: timm ==0.5.4
Requires-Dist: orjson
Requires-Dist: opencv-python-headless
Requires-Dist: datasets[vision]
Requires-Dist: lightning <2022,>=2.0.0
Requires-Dist: nltk
Requires-Dist: python-Levenshtein
Requires-Dist: sentencepiece
Requires-Dist: sconf >=0.2.3
Requires-Dist: albumentations >=1.0.0
Requires-Dist: pypdf >=3.1.0
Requires-Dist: pypdfium2
Provides-Extra: api
Requires-Dist: fastapi ; extra == 'api'
Requires-Dist: uvicorn[standard] ; extra == 'api'
Requires-Dist: python-multipart ; extra == 'api'
Provides-Extra: dataset
Requires-Dist: pytesseract ; extra == 'dataset'
Requires-Dist: beautifulsoup4 ; extra == 'dataset'
Requires-Dist: scikit-learn ; extra == 'dataset'
Requires-Dist: Pebble ; extra == 'dataset'
Requires-Dist: pylatexenc ; extra == 'dataset'
Requires-Dist: fuzzysearch ; extra == 'dataset'
Requires-Dist: unidecode ; extra == 'dataset'
Requires-Dist: htmlmin ; extra == 'dataset'
Requires-Dist: pdfminer.six >=20221105 ; extra == 'dataset'
